README.md
intensify.py
setup.py
python_intensifies.egg-info/PKG-INFO
python_intensifies.egg-info/SOURCES.txt
python_intensifies.egg-info/dependency_links.txt
python_intensifies.egg-info/entry_points.txt
python_intensifies.egg-info/requires.txt
python_intensifies.egg-info/top_level.txt