Metadata-Version: 2.1
Name: python-intensifies
Version: 0.2.1
Summary: A tool for INTENSIFYING images.
Home-page: https://github.com/CarvellScott/
Author: Carvell Scott
Author-email: carvell.scott@gmail.com
License: UNKNOWN
Keywords: intensify intensifies shaking memes
Platform: UNKNOWN
Classifier: Development Status :: 3 - Alpha
Classifier: Intended Audience :: End Users/Desktop
Classifier: Topic :: Artistic Software
Classifier: License :: OSI Approved :: MIT License
Classifier: Programming Language :: Python :: 3
Classifier: Programming Language :: Python :: 3.5
Classifier: Programming Language :: Python :: 3.6
